llmtestr/__init__.py
llmtestr/main.py
llmtestr/prompts.py
llmtestr-2025.12.21135641.dist-info/METADATA
llmtestr-2025.12.21135641.dist-info/WHEEL
llmtestr-2025.12.21135641.dist-info/top_level.txt
llmtestr-2025.12.21135641.dist-info/RECORD
