Metadata-Version: 2.4
Name: llmtestr
Version: 2025.12.21135641
Summary: A new package that helps developers integration-test AI and LLM applications by validating structured outputs. It takes a user's test scenario or prompt as input, sends it to an LLM, and uses pattern
Author-email: llmtestr <hi@eugene.plus>
License: MIT
Project-URL: Homepage, https://github.com/chigwell/llmtestr
Requires-Python: >=3.9
Requires-Dist: langchain-llm7>=0.0.0
Requires-Dist: llmatch-messages>=0.0.0
Requires-Dist: langchain-core>=0.3.0
